gautodoc/__init__.py
gautodoc/__main__.py
gautodoc/build.py
gautodoc/cli.py
gautodoc/common.py
gautodoc/config.py
gautodoc/registry.py
gautodoc/template/index.html
gautodoc/template/modules/gautodoc.mjs
gautodoc/template/styles/gautodoc.css
gautodoc/template/styles/index.css
gautodoc-0.0.1.dist-info/METADATA
gautodoc-0.0.1.dist-info/WHEEL
gautodoc-0.0.1.dist-info/licenses/LICENSE.md
gautodoc-0.0.1.dist-info/RECORD
