Metadata-Version: 2.1
Name: gautodoc
Version: 0.0.1
Summary: stupid simple autodoc
Project-URL: Homepage, https://github.com/garrisonhh/gautodoc
Project-URL: Bug Tracker, https://github.com/garrisonhh/gautodoc/issues
Author-email: Garrison Hinson-Hasty <garrisonhh+dev@pm.me>
License-File: LICENSE.md
Classifier: License :: Free To Use But Restricted
Classifier: Operating System :: POSIX :: Linux
Classifier: Programming Language :: Python :: 3
Classifier: Programming Language :: Python :: 3.10
Classifier: Programming Language :: Python :: 3.11
Classifier: Topic :: Documentation
Requires-Python: >=3.10
